dockeroo
tests
