Metadata-Version: 1.1
Name: dockeroo
Version: 0.35
Summary: Docker buildout recipe
Home-page: http://dockeroo.com/
Author: Giacomo Cariello
Author-email: info@dockeroo.com
License: Apache Software License (http://www.apache.org/licenses/LICENSE-2.0)
Download-URL: https://github.com/dockeroo/dockeroo/tarball/0.35
Keywords: buildout,docker
Platform: UNKNOWN
Classifier: Programming Language :: Python :: 2.7
Classifier: Programming Language :: Python :: 3
Classifier: License :: OSI Approved :: Apache Software License
Classifier: Development Status :: 4 - Beta
Classifier: Operating System :: OS Independent
Classifier: Framework :: Buildout
Classifier: Intended Audience :: Developers
Classifier: Topic :: Software Development :: Build Tools
Classifier: Topic :: Software Development :: Libraries :: Python Modules
Classifier: Topic :: System :: Systems Administration
